{
  "test": {
    "split": "test",
    "reward": 0.6759999999999999,
    "stderr": 0.05005792562988749,
    "pass_k": {
      "1": 0.6759999999999999,
      "2": 0.556
    },
    "pass_at_k": {
      "1": 0.6759999999999999,
      "2": 0.7959999999999999
    },
    "per_task": [
      {
        "task_id": "0",
        "reward": 0.9,
        "feedback": "Task reward: 0.000. Database state does NOT match the expected final state \u2014 a required write (book/update/cancel) was missing, wrong, or extra. See the per-action detail below for the specific wrong argument.",
        "n": 10,
        "stderr": 0.1,
        "trial_rewards": [
          1.0,
          1.0,
          1.0,
          1.0,
          1.0,
          1.0,
          1.0,
          1.0,
          1.0,
          0.0
        ],
        "raw": {
          "errored": false,
          "errored_trials": 0,
          "n_trials": 10
        }
      },
      {
        "task_id": "1",
        "reward": 0.2,
        "feedback": "Task reward: 0.000. Database state does NOT match the expected final state \u2014 a required write (book/update/cancel) was missing, wrong, or extra. See the per-action detail below for the specific wrong argument. Action-level defects (your own wrong values): get_user_details: was never called (or not called correctly); get_reservation_details: was never called (or not called correctly).",
        "n": 10,
        "stderr": 0.13333333333333336,
        "trial_rewards": [
          0.0,
          0.0,
          0.0,
          0.0,
          1.0,
          0.0,
          0.0,
          1.0,
          0.0,
          0.0
        ],
        "raw": {
          "errored": false,
          "errored_trials": 0,
          "n_trials": 10
        }
      },
      {
        "task_id": "2",
        "reward": 1.0,
        "feedback": "Task reward: 1.000. Action-level defects (your own wrong values): get_reservation_details: was never called (or not called correctly); get_reservation_details: was never called (or not called correctly).",
        "n": 10,
        "stderr": 0.0,
        "trial_rewards": [
          1.0,
          1.0,
          1.0,
          1.0,
          1.0,
          1.0,
          1.0,
          1.0,
          1.0,
          1.0
        ],
        "raw": {
          "errored": false,
          "errored_trials": 0,
          "n_trials": 10
        }
      },
      {
        "task_id": "3",
        "reward": 1.0,
        "feedback": "Task reward: 1.000. All checks passed.",
        "n": 10,
        "stderr": 0.0,
        "trial_rewards": [
          1.0,
          1.0,
          1.0,
          1.0,
          1.0,
          1.0,
          1.0,
          1.0,
          1.0,
          1.0
        ],
        "raw": {
          "errored": false,
          "errored_trials": 0,
          "n_trials": 10
        }
      },
      {
        "task_id": "4",
        "reward": 1.0,
        "feedback": "Task reward: 1.000. Action-level defects (your own wrong values): get_reservation_details: agent used reservation_id='AB742-20240412-SC-001' (not among the user's reservations; held=['NM1VX1', 'KC18K6', 'S61CZX', 'H8Q05L', 'WUNA5K']); get_reservation_details: agent used reservation_id='AB742-20240412-SC-001' (not among the user's reservations; held=['NM1VX1', 'KC18K6', 'S61CZX', 'H8Q05L', 'WUNA5K']); get_reservation_details: agent used reservation_id='AB742-20240412-SC-001' (not among the user's reservations; held=['NM1VX1', 'KC18K6', 'S61CZX', 'H8Q05L', 'WUNA5K']); get_reservation_details: agent used reservation_id='AB742-20240412-SC-001' (not among the user's reservations; held=['NM1VX1', 'KC18K6', 'S61CZX', 'H8Q05L', 'WUNA5K']); get_reservation_details: agent used reservation_id='AB742-20240412-SC-001' (not among the user's reservations; held=['NM1VX1', 'KC18K6', 'S61CZX', 'H8Q05L', 'WUNA5K']).",
        "n": 10,
        "stderr": 0.0,
        "trial_rewards": [
          1.0,
          1.0,
          1.0,
          1.0,
          1.0,
          1.0,
          1.0,
          1.0,
          1.0,
          1.0
        ],
        "raw": {
          "errored": false,
          "errored_trials": 0,
          "n_trials": 10
        }
      },
      {
        "task_id": "5",
        "reward": 0.8,
        "feedback": "Task reward: 1.000. Action-level defects (your own wrong values): get_user_details: was never called (or not called correctly).",
        "n": 10,
        "stderr": 0.13333333333333333,
        "trial_rewards": [
          1.0,
          1.0,
          0.0,
          0.0,
          1.0,
          1.0,
          1.0,
          1.0,
          1.0,
          1.0
        ],
        "raw": {
          "errored": false,
          "errored_trials": 0,
          "n_trials": 10
        }
      },
      {
        "task_id": "6",
        "reward": 0.6,
        "feedback": "Task reward: 1.000. All checks passed.",
        "n": 10,
        "stderr": 0.16329931618554522,
        "trial_rewards": [
          1.0,
          0.0,
          1.0,
          1.0,
          0.0,
          1.0,
          0.0,
          0.0,
          1.0,
          1.0
        ],
        "raw": {
          "errored": false,
          "errored_trials": 0,
          "n_trials": 10
        }
      },
      {
        "task_id": "7",
        "reward": 0.0,
        "feedback": "Task reward: 0.000. Database state does NOT match the expected final state \u2014 a required write (book/update/cancel) was missing, wrong, or extra. See the per-action detail below for the specific wrong argument. Action-level defects (your own wrong values): update_reservation_flights: was never called (or not called correctly); cancel_reservation: was never called (or not called correctly); cancel_reservation: was never called (or not called correctly). 1 required piece(s) of information were not clearly communicated to the user. State the confirmations/details (e.g. the computed total, the new flight times) the policy requires you to convey.",
        "n": 10,
        "stderr": 0.0,
        "trial_rewards": [
          0.0,
          0.0,
          0.0,
          0.0,
          0.0,
          0.0,
          0.0,
          0.0,
          0.0,
          0.0
        ],
        "raw": {
          "errored": false,
          "errored_trials": 0,
          "n_trials": 10
        }
      },
      {
        "task_id": "8",
        "reward": 1.0,
        "feedback": "Task reward: 1.000. Action-level defects (your own wrong values): get_reservation_details: was never called (or not called correctly).",
        "n": 10,
        "stderr": 0.0,
        "trial_rewards": [
          1.0,
          1.0,
          1.0,
          1.0,
          1.0,
          1.0,
          1.0,
          1.0,
          1.0,
          1.0
        ],
        "raw": {
          "errored": false,
          "errored_trials": 0,
          "n_trials": 10
        }
      },
      {
        "task_id": "9",
        "reward": 1.0,
        "feedback": "Task reward: 1.000. All checks passed.",
        "n": 10,
        "stderr": 0.0,
        "trial_rewards": [
          1.0,
          1.0,
          1.0,
          1.0,
          1.0,
          1.0,
          1.0,
          1.0,
          1.0,
          1.0
        ],
        "raw": {
          "errored": false,
          "errored_trials": 0,
          "n_trials": 10
        }
      },
      {
        "task_id": "10",
        "reward": 0.2,
        "feedback": "Task reward: 0.000. Database state does NOT match the expected final state \u2014 a required write (book/update/cancel) was missing, wrong, or extra. See the per-action detail below for the specific wrong argument.",
        "n": 10,
        "stderr": 0.13333333333333336,
        "trial_rewards": [
          0.0,
          0.0,
          0.0,
          1.0,
          0.0,
          1.0,
          0.0,
          0.0,
          0.0,
          0.0
        ],
        "raw": {
          "errored": false,
          "errored_trials": 0,
          "n_trials": 10
        }
      },
      {
        "task_id": "11",
        "reward": 0.4,
        "feedback": "Task reward: 1.000. All checks passed.",
        "n": 10,
        "stderr": 0.16329931618554522,
        "trial_rewards": [
          0.0,
          1.0,
          0.0,
          1.0,
          0.0,
          0.0,
          0.0,
          1.0,
          0.0,
          1.0
        ],
        "raw": {
          "errored": false,
          "errored_trials": 0,
          "n_trials": 10
        }
      },
      {
        "task_id": "12",
        "reward": 0.8,
        "feedback": "Task reward: 1.000. Action-level defects (your own wrong values): calculate: was never called (or not called correctly).",
        "n": 10,
        "stderr": 0.13333333333333333,
        "trial_rewards": [
          1.0,
          1.0,
          0.0,
          1.0,
          0.0,
          1.0,
          1.0,
          1.0,
          1.0,
          1.0
        ],
        "raw": {
          "errored": false,
          "errored_trials": 0,
          "n_trials": 10
        }
      },
      {
        "task_id": "13",
        "reward": 1.0,
        "feedback": "Task reward: 1.000. All checks passed.",
        "n": 10,
        "stderr": 0.0,
        "trial_rewards": [
          1.0,
          1.0,
          1.0,
          1.0,
          1.0,
          1.0,
          1.0,
          1.0,
          1.0,
          1.0
        ],
        "raw": {
          "errored": false,
          "errored_trials": 0,
          "n_trials": 10
        }
      },
      {
        "task_id": "14",
        "reward": 0.3,
        "feedback": "Task reward: 0.000. Database state does NOT match the expected final state \u2014 a required write (book/update/cancel) was missing, wrong, or extra. See the per-action detail below for the specific wrong argument. Action-level defects (your own wrong values): cancel_reservation: agent used reservation_id='HATHAT'.",
        "n": 10,
        "stderr": 0.15275252316519464,
        "trial_rewards": [
          1.0,
          1.0,
          1.0,
          0.0,
          0.0,
          0.0,
          0.0,
          0.0,
          0.0,
          0.0
        ],
        "raw": {
          "errored": false,
          "errored_trials": 0,
          "n_trials": 10
        }
      },
      {
        "task_id": "15",
        "reward": 0.9,
        "feedback": "Task reward: 1.000. All checks passed.",
        "n": 10,
        "stderr": 0.1,
        "trial_rewards": [
          0.0,
          1.0,
          1.0,
          1.0,
          1.0,
          1.0,
          1.0,
          1.0,
          1.0,
          1.0
        ],
        "raw": {
          "errored": false,
          "errored_trials": 0,
          "n_trials": 10
        }
      },
      {
        "task_id": "16",
        "reward": 1.0,
        "feedback": "Task reward: 1.000. All checks passed.",
        "n": 10,
        "stderr": 0.0,
        "trial_rewards": [
          1.0,
          1.0,
          1.0,
          1.0,
          1.0,
          1.0,
          1.0,
          1.0,
          1.0,
          1.0
        ],
        "raw": {
          "errored": false,
          "errored_trials": 0,
          "n_trials": 10
        }
      },
      {
        "task_id": "17",
        "reward": 0.8,
        "feedback": "Task reward: 1.000. All checks passed.",
        "n": 10,
        "stderr": 0.13333333333333333,
        "trial_rewards": [
          1.0,
          1.0,
          0.0,
          1.0,
          1.0,
          1.0,
          1.0,
          0.0,
          1.0,
          1.0
        ],
        "raw": {
          "errored": false,
          "errored_trials": 0,
          "n_trials": 10
        }
      },
      {
        "task_id": "18",
        "reward": 0.1,
        "feedback": "Task reward: 0.000. 1 required piece(s) of information were not clearly communicated to the user. State the confirmations/details (e.g. the computed total, the new flight times) the policy requires you to convey.",
        "n": 10,
        "stderr": 0.1,
        "trial_rewards": [
          1.0,
          0.0,
          0.0,
          0.0,
          0.0,
          0.0,
          0.0,
          0.0,
          0.0,
          0.0
        ],
        "raw": {
          "errored": false,
          "errored_trials": 0,
          "n_trials": 10
        }
      },
      {
        "task_id": "19",
        "reward": 0.5,
        "feedback": "Task reward: 0.000. Database state does NOT match the expected final state \u2014 a required write (book/update/cancel) was missing, wrong, or extra. See the per-action detail below for the specific wrong argument. Action-level defects (your own wrong values): cancel_reservation: was never called (or not called correctly).",
        "n": 10,
        "stderr": 0.16666666666666669,
        "trial_rewards": [
          0.0,
          0.0,
          1.0,
          1.0,
          1.0,
          0.0,
          1.0,
          1.0,
          0.0,
          0.0
        ],
        "raw": {
          "errored": false,
          "errored_trials": 0,
          "n_trials": 10
        }
      },
      {
        "task_id": "20",
        "reward": 0.8,
        "feedback": "Task reward: 1.000. All checks passed.",
        "n": 10,
        "stderr": 0.13333333333333333,
        "trial_rewards": [
          0.0,
          1.0,
          1.0,
          1.0,
          1.0,
          1.0,
          1.0,
          1.0,
          0.0,
          1.0
        ],
        "raw": {
          "errored": false,
          "errored_trials": 0,
          "n_trials": 10
        }
      },
      {
        "task_id": "21",
        "reward": 0.2,
        "feedback": "Task reward: 1.000. All checks passed.",
        "n": 10,
        "stderr": 0.13333333333333336,
        "trial_rewards": [
          0.0,
          0.0,
          1.0,
          0.0,
          0.0,
          0.0,
          0.0,
          0.0,
          0.0,
          1.0
        ],
        "raw": {
          "errored": false,
          "errored_trials": 0,
          "n_trials": 10
        }
      },
      {
        "task_id": "22",
        "reward": 0.6,
        "feedback": "Task reward: 1.000. All checks passed.",
        "n": 10,
        "stderr": 0.16329931618554522,
        "trial_rewards": [
          1.0,
          0.0,
          1.0,
          1.0,
          0.0,
          1.0,
          1.0,
          0.0,
          0.0,
          1.0
        ],
        "raw": {
          "errored": false,
          "errored_trials": 0,
          "n_trials": 10
        }
      },
      {
        "task_id": "23",
        "reward": 0.6,
        "feedback": "Task reward: 0.000. Database state does NOT match the expected final state \u2014 a required write (book/update/cancel) was missing, wrong, or extra. See the per-action detail below for the specific wrong argument. Action-level defects (your own wrong values): cancel_reservation: agent used reservation_id='K1NW8N'; book_reservation: agent used cabin='business', destination='SFO', flight_type='round_trip', flights=[{'flight_number': 'HAT023', 'date': '2024-05-26'}, {'flight_number': 'HAT204', 'date': '2024-05-28'}, {'flight_number': 'HAT100', 'date': '2024-05-28'}], insurance='no', nonfree_baggages=0, origin='JFK', passengers=[{'first_name': 'Mohamed', 'last_name': 'Silva', 'dob': '1960-11-26'}, {'first_name': 'Raj', 'last_name': 'Sanchez', 'dob': '1986-09-12'}, {'first_name': 'Liam', 'last_name': 'Wilson', 'dob': '1980-03-27'}], payment_methods=[{'payment_id': 'certificate_3765853', 'amount': 500}, {'payment_id': 'gift_card_8020792', 'amount': 198}, {'payment_id': 'gift_card_6136092', 'amount': 129}, {'payment_id': 'credit_card_2198526', 'amount': 1786}] (not on the user's profile; available=['credit_card_5843230', 'gift_card_8020792', 'certificate_3765853', 'gift_card_6136092', 'certificate_9984806', 'credit_card_2198526', 'certificate_2765295']), total_baggages=0, user_id='mohamed_silva_9265'; book_reservation: agent used cabin='business', destination='SFO', flight_type='round_trip', flights=[{'flight_number': 'HAT023', 'date': '2024-05-26'}, {'flight_number': 'HAT204', 'date': '2024-05-28'}, {'flight_number': 'HAT100', 'date': '2024-05-28'}], insurance='no', nonfree_baggages=0, origin='JFK', passengers=[{'first_name': 'Mohamed', 'last_name': 'Silva', 'dob': '1960-11-26'}, {'first_name': 'Raj', 'last_name': 'Sanchez', 'dob': '1986-09-12'}, {'first_name': 'Liam', 'last_name': 'Wilson', 'dob': '1980-03-27'}], payment_methods=[{'payment_id': 'certificate_3765853', 'amount': 500}, {'payment_id': 'gift_card_8020792', 'amount': 198}, {'payment_id': 'gift_card_6136092', 'amount': 129}, {'payment_id': 'credit_card_2198526', 'amount': 1786}] (not on the user's profile; available=['credit_card_5843230', 'gift_card_8020792', 'certificate_3765853', 'gift_card_6136092', 'certificate_9984806', 'credit_card_2198526', 'certificate_2765295']), total_baggages=0, user_id='mohamed_silva_9265'; book_reservation: agent used cabin='business', destination='SFO', flight_type='round_trip', flights=[{'flight_number': 'HAT023', 'date': '2024-05-26'}, {'flight_number': 'HAT204', 'date': '2024-05-28'}, {'flight_number': 'HAT100', 'date': '2024-05-28'}], insurance='no', nonfree_baggages=0, origin='JFK', passengers=[{'first_name': 'Mohamed', 'last_name': 'Silva', 'dob': '1960-11-26'}, {'first_name': 'Raj', 'last_name': 'Sanchez', 'dob': '1986-09-12'}, {'first_name': 'Liam', 'last_name': 'Wilson', 'dob': '1980-03-27'}], payment_methods=[{'payment_id': 'certificate_3765853', 'amount': 500}, {'payment_id': 'gift_card_8020792', 'amount': 198}, {'payment_id': 'gift_card_6136092', 'amount': 129}, {'payment_id': 'credit_card_2198526', 'amount': 1786}] (not on the user's profile; available=['credit_card_5843230', 'gift_card_8020792', 'certificate_3765853', 'gift_card_6136092', 'certificate_9984806', 'credit_card_2198526', 'certificate_2765295']), total_baggages=0, user_id='mohamed_silva_9265'. 1 required piece(s) of information were not clearly communicated to the user. State the confirmations/details (e.g. the computed total, the new flight times) the policy requires you to convey.",
        "n": 10,
        "stderr": 0.16329931618554522,
        "trial_rewards": [
          1.0,
          0.0,
          1.0,
          1.0,
          1.0,
          1.0,
          1.0,
          0.0,
          0.0,
          0.0
        ],
        "raw": {
          "errored": false,
          "errored_trials": 0,
          "n_trials": 10
        }
      },
      {
        "task_id": "24",
        "reward": 0.1,
        "feedback": "Task reward: 0.000. Database state does NOT match the expected final state \u2014 a required write (book/update/cancel) was missing, wrong, or extra. See the per-action detail below for the specific wrong argument. Action-level defects (your own wrong values): book_reservation: agent used cabin='basic_economy', destination='LAX', flight_type='round_trip', flights=[{'flight_number': 'HAT041', 'date': '2024-05-20'}, {'flight_number': 'HAT012', 'date': '2024-05-25'}], insurance='no', nonfree_baggages=0, origin='EWR', passengers=[{'first_name': 'Mia', 'last_name': 'Kim', 'dob': '1965-06-09'}], payment_methods=[{'payment_id': 'gift_card_7359776', 'amount': 39}, {'payment_id': 'gift_card_7773485', 'amount': 124}] (not on the user's profile; available=['gift_card_7359776', 'gift_card_7773485']), total_baggages=1, user_id='mia_kim_4397'.",
        "n": 10,
        "stderr": 0.1,
        "trial_rewards": [
          0.0,
          1.0,
          0.0,
          0.0,
          0.0,
          0.0,
          0.0,
          0.0,
          0.0,
          0.0
        ],
        "raw": {
          "errored": false,
          "errored_trials": 0,
          "n_trials": 10
        }
      },
      {
        "task_id": "25",
        "reward": 0.8,
        "feedback": "Task reward: 1.000. All checks passed.",
        "n": 10,
        "stderr": 0.13333333333333333,
        "trial_rewards": [
          1.0,
          1.0,
          1.0,
          1.0,
          0.0,
          1.0,
          0.0,
          1.0,
          1.0,
          1.0
        ],
        "raw": {
          "errored": false,
          "errored_trials": 0,
          "n_trials": 10
        }
      },
      {
        "task_id": "26",
        "reward": 1.0,
        "feedback": "Task reward: 1.000. All checks passed.",
        "n": 10,
        "stderr": 0.0,
        "trial_rewards": [
          1.0,
          1.0,
          1.0,
          1.0,
          1.0,
          1.0,
          1.0,
          1.0,
          1.0,
          1.0
        ],
        "raw": {
          "errored": false,
          "errored_trials": 0,
          "n_trials": 10
        }
      },
      {
        "task_id": "27",
        "reward": 1.0,
        "feedback": "Task reward: 1.000. Action-level defects (your own wrong values): get_user_details: was never called (or not called correctly).",
        "n": 10,
        "stderr": 0.0,
        "trial_rewards": [
          1.0,
          1.0,
          1.0,
          1.0,
          1.0,
          1.0,
          1.0,
          1.0,
          1.0,
          1.0
        ],
        "raw": {
          "errored": false,
          "errored_trials": 0,
          "n_trials": 10
        }
      },
      {
        "task_id": "28",
        "reward": 1.0,
        "feedback": "Task reward: 1.000. All checks passed.",
        "n": 10,
        "stderr": 0.0,
        "trial_rewards": [
          1.0,
          1.0,
          1.0,
          1.0,
          1.0,
          1.0,
          1.0,
          1.0,
          1.0,
          1.0
        ],
        "raw": {
          "errored": false,
          "errored_trials": 0,
          "n_trials": 10
        }
      },
      {
        "task_id": "29",
        "reward": 0.6,
        "feedback": "Task reward: 1.000. Action-level defects (your own wrong values): cancel_reservation: agent used reservation_id='VA5SGQ'.",
        "n": 10,
        "stderr": 0.16329931618554522,
        "trial_rewards": [
          0.0,
          1.0,
          1.0,
          1.0,
          0.0,
          0.0,
          0.0,
          1.0,
          1.0,
          1.0
        ],
        "raw": {
          "errored": false,
          "errored_trials": 0,
          "n_trials": 10
        }
      },
      {
        "task_id": "30",
        "reward": 0.9,
        "feedback": "Task reward: 1.000. All checks passed.",
        "n": 10,
        "stderr": 0.1,
        "trial_rewards": [
          1.0,
          1.0,
          1.0,
          1.0,
          1.0,
          1.0,
          0.0,
          1.0,
          1.0,
          1.0
        ],
        "raw": {
          "errored": false,
          "errored_trials": 0,
          "n_trials": 10
        }
      },
      {
        "task_id": "31",
        "reward": 0.6,
        "feedback": "Task reward: 1.000. All checks passed.",
        "n": 10,
        "stderr": 0.16329931618554522,
        "trial_rewards": [
          1.0,
          0.0,
          1.0,
          1.0,
          0.0,
          1.0,
          0.0,
          0.0,
          1.0,
          1.0
        ],
        "raw": {
          "errored": false,
          "errored_trials": 0,
          "n_trials": 10
        }
      },
      {
        "task_id": "32",
        "reward": 0.3,
        "feedback": "Task reward: 0.000. Database state does NOT match the expected final state \u2014 a required write (book/update/cancel) was missing, wrong, or extra. See the per-action detail below for the specific wrong argument. Action-level defects (your own wrong values): get_user_details: was never called (or not called correctly); get_reservation_details: was never called (or not called correctly); update_reservation_flights: was never called (or not called correctly); update_reservation_flights: was never called (or not called correctly).",
        "n": 10,
        "stderr": 0.15275252316519464,
        "trial_rewards": [
          0.0,
          1.0,
          0.0,
          1.0,
          0.0,
          0.0,
          1.0,
          0.0,
          0.0,
          0.0
        ],
        "raw": {
          "errored": false,
          "errored_trials": 0,
          "n_trials": 10
        }
      },
      {
        "task_id": "33",
        "reward": 0.8,
        "feedback": "Task reward: 1.000. Action-level defects (your own wrong values): search_direct_flight: agent used date='2024-05-23', destination='IAH', origin='SFO'.",
        "n": 10,
        "stderr": 0.13333333333333333,
        "trial_rewards": [
          1.0,
          1.0,
          1.0,
          1.0,
          1.0,
          0.0,
          1.0,
          1.0,
          0.0,
          1.0
        ],
        "raw": {
          "errored": false,
          "errored_trials": 0,
          "n_trials": 10
        }
      },
      {
        "task_id": "34",
        "reward": 1.0,
        "feedback": "Task reward: 1.000. All checks passed.",
        "n": 10,
        "stderr": 0.0,
        "trial_rewards": [
          1.0,
          1.0,
          1.0,
          1.0,
          1.0,
          1.0,
          1.0,
          1.0,
          1.0,
          1.0
        ],
        "raw": {
          "errored": false,
          "errored_trials": 0,
          "n_trials": 10
        }
      },
      {
        "task_id": "35",
        "reward": 0.5,
        "feedback": "Task reward: 0.000. Database state does NOT match the expected final state \u2014 a required write (book/update/cancel) was missing, wrong, or extra. See the per-action detail below for the specific wrong argument. Action-level defects (your own wrong values): book_reservation: agent used cabin='economy', destination='SFO', flight_type='one_way', flights=[{'flight_number': 'HAT023', 'date': '2024-05-24'}], insurance='no', nonfree_baggages=0, origin='JFK', passengers=[{'first_name': 'Aarav', 'last_name': 'Ahmed', 'dob': '1981-05-26'}], payment_methods=[{'payment_id': 'credit_card_9074831', 'amount': 163}] (not on the user's profile; available=['credit_card_4959530', 'credit_card_9074831', 'certificate_9645872']), total_baggages=0, user_id='aarav_ahmed_6699'.",
        "n": 10,
        "stderr": 0.16666666666666669,
        "trial_rewards": [
          1.0,
          1.0,
          1.0,
          1.0,
          0.0,
          0.0,
          0.0,
          1.0,
          0.0,
          0.0
        ],
        "raw": {
          "errored": false,
          "errored_trials": 0,
          "n_trials": 10
        }
      },
      {
        "task_id": "36",
        "reward": 1.0,
        "feedback": "Task reward: 1.000. All checks passed.",
        "n": 10,
        "stderr": 0.0,
        "trial_rewards": [
          1.0,
          1.0,
          1.0,
          1.0,
          1.0,
          1.0,
          1.0,
          1.0,
          1.0,
          1.0
        ],
        "raw": {
          "errored": false,
          "errored_trials": 0,
          "n_trials": 10
        }
      },
      {
        "task_id": "37",
        "reward": 0.7,
        "feedback": "Task reward: 1.000. Action-level defects (your own wrong values): get_reservation_details: was never called (or not called correctly).",
        "n": 10,
        "stderr": 0.15275252316519466,
        "trial_rewards": [
          1.0,
          1.0,
          0.0,
          1.0,
          0.0,
          1.0,
          1.0,
          0.0,
          1.0,
          1.0
        ],
        "raw": {
          "errored": false,
          "errored_trials": 0,
          "n_trials": 10
        }
      },
      {
        "task_id": "38",
        "reward": 0.8,
        "feedback": "Task reward: 1.000. Action-level defects (your own wrong values): get_user_details: was never called (or not called correctly); get_reservation_details: was never called (or not called correctly).",
        "n": 10,
        "stderr": 0.13333333333333333,
        "trial_rewards": [
          1.0,
          1.0,
          1.0,
          0.0,
          1.0,
          0.0,
          1.0,
          1.0,
          1.0,
          1.0
        ],
        "raw": {
          "errored": false,
          "errored_trials": 0,
          "n_trials": 10
        }
      },
      {
        "task_id": "39",
        "reward": 1.0,
        "feedback": "Task reward: 1.000. Action-level defects (your own wrong values): get_user_details: was never called (or not called correctly); get_reservation_details: was never called (or not called correctly); get_reservation_details: was never called (or not called correctly); get_reservation_details: was never called (or not called correctly); get_reservation_details: was never called (or not called correctly); get_reservation_details: was never called (or not called correctly); get_reservation_details: was never called (or not called correctly); get_reservation_details: was never called (or not called correctly); cancel_reservation: agent used reservation_id='MSJ4OA'; cancel_reservation: agent used reservation_id='MSJ4OA'; cancel_reservation: agent used reservation_id='MSJ4OA'.",
        "n": 10,
        "stderr": 0.0,
        "trial_rewards": [
          1.0,
          1.0,
          1.0,
          1.0,
          1.0,
          1.0,
          1.0,
          1.0,
          1.0,
          1.0
        ],
        "raw": {
          "errored": false,
          "errored_trials": 0,
          "n_trials": 10
        }
      },
      {
        "task_id": "40",
        "reward": 0.3,
        "feedback": "Task reward: 0.000. Database state does NOT match the expected final state \u2014 a required write (book/update/cancel) was missing, wrong, or extra. See the per-action detail below for the specific wrong argument. Action-level defects (your own wrong values): update_reservation_passengers: was never called (or not called correctly).",
        "n": 10,
        "stderr": 0.15275252316519464,
        "trial_rewards": [
          1.0,
          1.0,
          0.0,
          0.0,
          1.0,
          0.0,
          0.0,
          0.0,
          0.0,
          0.0
        ],
        "raw": {
          "errored": false,
          "errored_trials": 0,
          "n_trials": 10
        }
      },
      {
        "task_id": "41",
        "reward": 1.0,
        "feedback": "Task reward: 1.000. Action-level defects (your own wrong values): get_user_details: was never called (or not called correctly); get_reservation_details: was never called (or not called correctly); get_reservation_details: was never called (or not called correctly); get_reservation_details: was never called (or not called correctly); get_reservation_details: was never called (or not called correctly); get_reservation_details: was never called (or not called correctly); get_reservation_details: was never called (or not called correctly); get_reservation_details: was never called (or not called correctly).",
        "n": 10,
        "stderr": 0.0,
        "trial_rewards": [
          1.0,
          1.0,
          1.0,
          1.0,
          1.0,
          1.0,
          1.0,
          1.0,
          1.0,
          1.0
        ],
        "raw": {
          "errored": false,
          "errored_trials": 0,
          "n_trials": 10
        }
      },
      {
        "task_id": "42",
        "reward": 0.0,
        "feedback": "Task reward: 0.000. Database state does NOT match the expected final state \u2014 a required write (book/update/cancel) was missing, wrong, or extra. See the per-action detail below for the specific wrong argument. Action-level defects (your own wrong values): get_user_details: was never called (or not called correctly); get_reservation_details: was never called (or not called correctly); get_reservation_details: was never called (or not called correctly); get_reservation_details: was never called (or not called correctly); get_reservation_details: was never called (or not called correctly); get_reservation_details: was never called (or not called correctly); get_reservation_details: was never called (or not called correctly); get_reservation_details: was never called (or not called correctly); cancel_reservation: was never called (or not called correctly); cancel_reservation: was never called (or not called correctly).",
        "n": 10,
        "stderr": 0.0,
        "trial_rewards": [
          0.0,
          0.0,
          0.0,
          0.0,
          0.0,
          0.0,
          0.0,
          0.0,
          0.0,
          0.0
        ],
        "raw": {
          "errored": false,
          "errored_trials": 0,
          "n_trials": 10
        }
      },
      {
        "task_id": "43",
        "reward": 0.4,
        "feedback": "Task reward: 1.000. Action-level defects (your own wrong values): get_user_details: was never called (or not called correctly); get_reservation_details: was never called (or not called correctly); get_reservation_details: was never called (or not called correctly); get_reservation_details: was never called (or not called correctly); get_reservation_details: was never called (or not called correctly); get_reservation_details: was never called (or not called correctly).",
        "n": 10,
        "stderr": 0.16329931618554522,
        "trial_rewards": [
          0.0,
          0.0,
          0.0,
          1.0,
          1.0,
          0.0,
          0.0,
          1.0,
          0.0,
          1.0
        ],
        "raw": {
          "errored": false,
          "errored_trials": 0,
          "n_trials": 10
        }
      },
      {
        "task_id": "44",
        "reward": 0.0,
        "feedback": "Task reward: 0.000. Database state does NOT match the expected final state \u2014 a required write (book/update/cancel) was missing, wrong, or extra. See the per-action detail below for the specific wrong argument. Action-level defects (your own wrong values): get_reservation_details: was never called (or not called correctly); get_reservation_details: was never called (or not called correctly); get_reservation_details: was never called (or not called correctly); get_reservation_details: was never called (or not called correctly); get_reservation_details: was never called (or not called correctly); search_direct_flight: agent used date='2024-05-25', destination='LAX', origin='EWR'; search_direct_flight: agent used date='2024-05-25', destination='LAX', origin='EWR'; update_reservation_flights: agent used cabin='business', flights=[{'flight_number': 'HAT268', 'date': '2024-05-24'}], payment_id='credit_card_4196779', reservation_id='H8Q05L'; update_reservation_flights: agent used cabin='business', flights=[{'flight_number': 'HAT268', 'date': '2024-05-24'}], payment_id='credit_card_4196779', reservation_id='H8Q05L'.",
        "n": 10,
        "stderr": 0.0,
        "trial_rewards": [
          0.0,
          0.0,
          0.0,
          0.0,
          0.0,
          0.0,
          0.0,
          0.0,
          0.0,
          0.0
        ],
        "raw": {
          "errored": false,
          "errored_trials": 0,
          "n_trials": 10
        }
      },
      {
        "task_id": "45",
        "reward": 0.9,
        "feedback": "Task reward: 1.000. All checks passed.",
        "n": 10,
        "stderr": 0.1,
        "trial_rewards": [
          1.0,
          1.0,
          1.0,
          1.0,
          1.0,
          0.0,
          1.0,
          1.0,
          1.0,
          1.0
        ],
        "raw": {
          "errored": false,
          "errored_trials": 0,
          "n_trials": 10
        }
      },
      {
        "task_id": "46",
        "reward": 1.0,
        "feedback": "Task reward: 1.000. All checks passed.",
        "n": 10,
        "stderr": 0.0,
        "trial_rewards": [
          1.0,
          1.0,
          1.0,
          1.0,
          1.0,
          1.0,
          1.0,
          1.0,
          1.0,
          1.0
        ],
        "raw": {
          "errored": false,
          "errored_trials": 0,
          "n_trials": 10
        }
      },
      {
        "task_id": "47",
        "reward": 0.4,
        "feedback": "Task reward: 1.000. All checks passed.",
        "n": 10,
        "stderr": 0.16329931618554522,
        "trial_rewards": [
          0.0,
          0.0,
          1.0,
          1.0,
          0.0,
          1.0,
          0.0,
          0.0,
          0.0,
          1.0
        ],
        "raw": {
          "errored": false,
          "errored_trials": 0,
          "n_trials": 10
        }
      },
      {
        "task_id": "48",
        "reward": 1.0,
        "feedback": "Task reward: 1.000. Action-level defects (your own wrong values): get_reservation_details: was never called (or not called correctly).",
        "n": 10,
        "stderr": 0.0,
        "trial_rewards": [
          1.0,
          1.0,
          1.0,
          1.0,
          1.0,
          1.0,
          1.0,
          1.0,
          1.0,
          1.0
        ],
        "raw": {
          "errored": false,
          "errored_trials": 0,
          "n_trials": 10
        }
      },
      {
        "task_id": "49",
        "reward": 1.0,
        "feedback": "Task reward: 1.000. All checks passed.",
        "n": 10,
        "stderr": 0.0,
        "trial_rewards": [
          1.0,
          1.0,
          1.0,
          1.0,
          1.0,
          1.0,
          1.0,
          1.0,
          1.0,
          1.0
        ],
        "raw": {
          "errored": false,
          "errored_trials": 0,
          "n_trials": 10
        }
      }
    ],
    "cost_usd": 0.0,
    "tokens": 0,
    "seconds": 1276.6784899234772
  },
  "best_id": "cand_0009"
}